{
    "battle": {
        "autobattle": true,
        "bossprot": false,
        "delayfrom": 4000,
        "delayto": 4500,
        "highspeed": true,
        "list": [
            {
                "condition": 0,
                "condition2": 0,
                "condition2rel": 0,
                "condition2val": "",
                "conditionrel": 0,
                "conditionval": "",
                "index": 0,
                "petaction": 100,
                "petskillname": "防御",
                "pettarget": 0,
                "pettargetsel": 0,
                "playeraction": 3,
                "playertarget": -1,
                "playertargetsel": -1
            }
        ],
        "lockcd": false,
        "lv1prot": false,
        "pet2action": false,
        "playerforceaction": false,
        "r1nodelay": false,
        "showhpmp": false
    },
    "chat": {
        "displayname": true,
        "displaytime": true,
        "mychat": true,
        "npcmsg": true,
        "playerchat": true,
        "sysmsg": true,
        "todayonly": true
    },
    "itemdroplist": [
        "地的水晶碎片",
        "水的水晶碎片",
        "火的水晶碎片",
        "风的水晶碎片"
    ],
    "itemidmap": {
    },
    "itemtweaklist": [
        "小麦粉|40",
        "牛奶|40",
        "盐|40",
        "酱油|40",
        "葱|40",
        "鸡肉|40",
        "牛肉|40",
        "胡椒|40",
        "砂糖|40",
        "苹果薄荷|40",
        "柠檬草|40"
    ],
    "player": {
        "autosupply": true,
        "movespd": 100,
        "noswitchanim": true,
        "workacc": 100,
        "workdelay": 1500
    }
}
